setup.py
impaka/__init__.py
impaka/impaka.py
impaka.egg-info/PKG-INFO
impaka.egg-info/SOURCES.txt
impaka.egg-info/dependency_links.txt
impaka.egg-info/not-zip-safe
impaka.egg-info/top_level.txt