Metadata-Version: 2.1
Name: impaka
Version: 1.0
Summary: Feature importance ranking
Home-page: UNKNOWN
License: UNKNOWN
Platform: UNKNOWN
